test.py
lest/__init__.py
lest/assertions.py
lest/registerer.py
lest/runner.py
lest/setup.py
lest-0.7.1.dist-info/LICENSE
lest-0.7.1.dist-info/METADATA
lest-0.7.1.dist-info/WHEEL
lest-0.7.1.dist-info/top_level.txt
lest-0.7.1.dist-info/RECORD
