Metadata-Version: 2.2
Name: lest
Version: 0.7.1
Summary: Light Python library for testing.
Author-email: wchistow <wchistow@yandex.ru>
Project-URL: Homepage, https://github.com/wchistow/lest
Project-URL: Bug Tracker, https://github.com/wchistow/lest/issues
Project-URL: Repository, https://github.com/wchistow/lest.git
Classifier: Development Status :: 5 - Production/Stable
Classifier: Programming Language :: Python :: 3
Classifier: Programming Language :: Python :: 3.9
Classifier: Programming Language :: Python :: 3.10
Classifier: Programming Language :: Python :: 3.11
Classifier: Programming Language :: Python :: 3.12
Classifier: Programming Language :: Python :: 3.13
Classifier: Programming Language :: Python :: 3 :: Only
Classifier: License :: OSI Approved :: MIT License
Classifier: Operating System :: OS Independent
Requires-Python: >=3.9
License-File: LICENSE
Requires-Dist: rich==13.9.4
